<?xml version="1.0" encoding="UTF-8"?><!DOCTYPE en-export SYSTEM "http://xml.evernote.com/pub/evernote-export2.dtd">
<en-export export-date="20210519T170149Z" application="Evernote/Windows" version="6.x">
    <note>
        <title>简历</title>
        <content><![CDATA[<!DOCTYPE en-note SYSTEM 'http://xml.evernote.com/pub/enml2.dtd'><en-note><center style='display:none !important;visibility:collapse !important;height:0 !important;white-space:nowrap;width:100%;overflow:hidden'>

</center></en-note>]]></content>
        <created>20210518T162631Z</created>
        <updated>20210518T171311Z</updated>
        <note-attributes>
            <author>羊羽</author>
            <source>desktop.win</source>
            <source-application>yinxiang.win32</source-application>
            <content-class>yinxiang.markdown</content-class>
        </note-attributes>
    </note>
</en-export>
